{
  "title": "RIK88",
  "packageName": "org.cocos2d.demo",
  "startScene": "28be5ba7-b801-41aa-8630-8758c14a1650",
  "excludeScenes": [
    "6f9093a0-fcd8-4667-a975-5b29de926494"
  ],
  "orientation": {
    "landscapeLeft": false,
    "landscapeRight": false,
    "portrait": true,
    "upsideDown": true
  },
  "webOrientation": "portrait",
  "inlineSpriteFrames": false,
  "inlineSpriteFrames_native": false,
  "mainCompressionType": "default",
  "mainIsRemote": false,
  "optimizeHotUpdate": false,
  "md5Cache": true,
  "nativeMd5Cache": false,
  "encryptJs": false,
  "xxteaKey": "52baila-poker",
  "zipCompressJs": true,
  "fb-instant-games": {},
  "android": {
    "REMOTE_SERVER_ROOT": "",
    "packageName": "com.rik88.asia"
  },
  "ios": {
    "REMOTE_SERVER_ROOT": "",
    "packageName": "com.tienlenmiennam.online"
  },
  "mac": {
    "REMOTE_SERVER_ROOT": "",
    "height": 720,
    "packageName": "org.cocos2d.demo",
    "width": 1280
  },
  "win32": {
    "REMOTE_SERVER_ROOT": "",
    "height": 720,
    "width": 1280
  },
  "android-instant": {
    "REMOTE_SERVER_ROOT": "",
    "host": "",
    "packageName": "org.cocos2d.demo",
    "pathPattern": "",
    "recordPath": "",
    "scheme": "https",
    "skipRecord": false
  },
  "appBundle": false
}
